ChemCompute/Kinetic.py
ChemCompute/Thermodynamic.py
ChemCompute/__init__.py
ChemCompute/_general.py
ChemCompute/test.py
chemcompute-0.1.1.dist-info/licenses/LICENSE
chemcompute-0.1.1.dist-info/METADATA
chemcompute-0.1.1.dist-info/WHEEL
chemcompute-0.1.1.dist-info/top_level.txt
chemcompute-0.1.1.dist-info/RECORD
