Metadata-Version: 2.4
Name: chemcompute
Version: 0.1.1
Summary: A Python library for chemical reaction simulation, including kinetic modeling and thermodynamic equilibrium calculations
Home-page: https://github.com/MohammadKeifari/ChemCompute
Author: Mohammad Keifari
Author-email: Mohammad Keifari <mohammadkeifari2007@gmail.com>
License: MIT
Project-URL: Homepage, https://github.com/MohammadKeifari/ChemCompute
Project-URL: Documentation, https://github.com/MohammadKeifari/ChemCompute#readme
Project-URL: Repository, https://github.com/MohammadKeifari/ChemCompute
Project-URL: Issues, https://github.com/yourusername/ChemCompute/issues
Keywords: chemistry,chemical reactions,kinetics,thermodynamics,equilibrium,simulation
Classifier: Development Status :: 3 - Alpha
Classifier: Intended Audience :: Science/Research
Classifier: Intended Audience :: Education
Classifier: Topic :: Scientific/Engineering :: Chemistry
Classifier: License :: OSI Approved :: MIT License
Classifier: Programming Language :: Python :: 3
Classifier: Programming Language :: Python :: 3.7
Classifier: Programming Language :: Python :: 3.8
Classifier: Programming Language :: Python :: 3.9
Classifier: Programming Language :: Python :: 3.10
Classifier: Programming Language :: Python :: 3.11
Classifier: Programming Language :: Python :: 3.12
Classifier: Operating System :: OS Independent
Requires-Python: >=3.7
License-File: LICENSE
Requires-Dist: numpy>=1.19.0
Requires-Dist: matplotlib>=3.3.0
Provides-Extra: dev
Requires-Dist: pytest>=6.0.0; extra == "dev"
Requires-Dist: pytest-cov>=2.0.0; extra == "dev"
Dynamic: author
Dynamic: home-page
Dynamic: license-file
Dynamic: requires-python
